{
  "__type__": "cc.Mesh",
  "_name": "",
  "_objFlags": 0,
  "__editorExtras__": {},
  "_native": ".bin",
  "_struct": {
    "primitives": [
      {
        "primitiveMode": 7,
        "vertexBundelIndices": [
          0
        ],
        "indexView": {
          "offset": 2832,
          "length": 504,
          "count": 252,
          "stride": 2
        }
      }
    ],
    "vertexBundles": [
      {
        "view": {
          "offset": 0,
          "length": 2832,
          "count": 59,
          "stride": 48
        },
        "attributes": [
          {
            "name": "a_position",
            "format": 32,
            "isNormalized": false
          },
          {
            "name": "a_normal",
            "format": 32,
            "isNormalized": false
          },
          {
            "name": "a_texCoord",
            "format": 21,
            "isNormalized": false
          },
          {
            "name": "a_tangent",
            "format": 44,
            "isNormalized": false
          }
        ]
      }
    ],
    "minPosition": {
      "__type__": "cc.Vec3",
      "x": -0.21604564785957336,
      "y": 0.23343944549560547,
      "z": -9.0481595993042
    },
    "maxPosition": {
      "__type__": "cc.Vec3",
      "x": 0.20156459510326385,
      "y": 0.7613378763198853,
      "z": -8.718771934509277
    }
  },
  "_hash": 2543124339,
  "_allowDataAccess": true
}